{
  "fieldSets": [
    {
      "fields": [
        {
          "defaultValue": false,
          "label": "lfr.misc.enable-debug",
          "description": "lfr.misc.enable-debug",
          "name": "enableDebug",
          "type": "checkbox"
        }
      ],
      "label": "lfr.misc.general"
    },
    {
      "fields": [
        {
          "defaultValue": true,
          "label": "lfr.misc.enable-menu-text",
          "description": "lfr.misc.enable-menu-text",
          "name": "enableMenuText",
          "type": "checkbox"
        },
        {
          "defaultValue": true,
          "label": "lfr.misc.run-menu-text-onload",
          "description": "lfr.misc.run-menu-text-onload",
          "name": "runMenuTextOnload",
          "type": "checkbox"
        },
        {
          "defaultValue": "My Profile",
          "description": "lfr.misc.menu-text-description",
          "label": "lfr.misc.menu-text",
          "name": "menuText",
          "type": "text"
        },
        {
          "defaultValue": "/profile",
          "description": "lfr.misc.page-link-description",
          "label": "lfr.misc.page-link",
          "name": "pageLink",
          "type": "text"
        }
      ],
      "label": "lfr.misc.navigation"
    }
  ]
}
